LICENSE
README.rst
tapshex/__init__.py
tapshex/classes.py
tapshex/config.py
tapshex/csvreader.py
tapshex/defaults.py
tapshex/shexify.py
tapshex/template.py
tapshex/utils.py
tapshex-0.2.3.dist-info/LICENSE
tapshex-0.2.3.dist-info/WHEEL
tapshex-0.2.3.dist-info/METADATA
tapshex-0.2.3.dist-info/RECORD
