Metadata-Version: 2.1
Name: tapshex
Version: 0.2.3
Summary: Converts TAP/CSV into ShEx Schema
Home-page: https://pypi.org/project/tapshex/
License: MIT
Author: Tom Baker
Author-email: tom@tombaker.org
Requires-Python: >=3.10,<4.0
Classifier: Development Status :: 3 - Alpha
Classifier: License :: OSI Approved :: MIT License
Classifier: Programming Language :: Python :: 3
Classifier: Programming Language :: Python :: 3.10
Classifier: Programming Language :: Python :: 3.11
Classifier: Programming Language :: Python :: 3.10
Classifier: Programming Language :: Python :: 3.11
Classifier: Programming Language :: Python :: 3.8
Classifier: Programming Language :: Python :: 3.9
Requires-Dist: Jinja2 (>=3.1.2,<4.0.0)
Requires-Dist: black (>=22.12.0,<23.0.0)
Requires-Dist: click (>=8.1.3,<9.0.0)
Requires-Dist: dctap (>=0.4.4,<0.5.0)
Requires-Dist: ipdb (>=0.13.11,<0.14.0)
Requires-Dist: ipykernel (>=6.20.1,<7.0.0)
Requires-Dist: ipython (==8.8.0)
Requires-Dist: jinja2-cli (>=0.8.2,<0.9.0)
Requires-Dist: pip-tools (>=6.12.1,<7.0.0)
Requires-Dist: pre-commit (>=2.21.0,<3.0.0)
Requires-Dist: pyshexc (>=0.9.1,<0.10.0)
Project-URL: Documentation, https://tapshex.readthedocs.io/en/latest
Project-URL: Repository, https://github.com/tombaker/tapshex
